rtta-0.1.10.dist-info/METADATA
rtta-0.1.10.dist-info/WHEEL
rtta.cpython-313-darwin.so
rtta-0.1.10.dist-info/RECORD
