Metadata-Version: 2.1
Name: rtta
Version: 0.1.10
Summary: Low latency incremental technical analysis
Author-Email: Adam DePrince <adam.deprince@gmail.com>
Requires-Python: >=3.9.8
Requires-Dist: numpy>=2.0.2
